[
  {
    "id": 26,
    "slug": "film",
    "name": "FILM"
  },
  {
     "id": 28,
    "slug": "schift",
    "name": "SCHIFT"
  },
  {
    "id": 33,
    "slug": "boeken",
    "name": "BOEKEN"
  },
  {
    "id": 9,
    "slug": "interview",
    "name": "INTERVIEW"
  },
  {
    "id": 27,
    "slug": "muziek",
    "name": "MUZIEK"
  },
  {
    "id": 20,
    "slug": "nrc",
    "name": "NRC"
  },
  {
    "id": 25,
    "slug": "recensie",
    "name": "RECENSIE"
  },
  {
    "id": 17,
    "slug": "covers",
    "name": "COVERS"
  },
  {
    "id": 32,
    "slug": "documentaire",
    "name": "DOCUMENTAIRE"
  },
  {
    "id": 31,
    "slug": "idfa",
    "name": "IDFA"
  },
  {
    "id": 13,
    "slug": "daily-tiger",
    "name": "DAILY TIGER"
  },
  {
    "id": 7,
    "slug": "iffr",
    "name": "IFFR"
  },
  {
    "id": 15,
    "slug": "literatuur",
    "name": "LITERATUUR"
  },
  {
    "id": 29,
    "slug": "comedy",
    "name": "COMEDY"
  },
  {
    "id": 10,
    "slug": "televisie",
    "name": "TELEVISIE"
  },
  {
    "id": 30,
    "slug": "tv",
    "name": "TV"
  },
  {
    "id": 34,
    "slug": "vpro-gids",
    "name": "VPRO GIDS"
  }
]